target_universal_file/__init__.py
target_universal_file/__main__.py
target_universal_file/filesystem.py
target_universal_file/sinks.py
target_universal_file/target.py
target_universal_file/writer.py
target_universal_file-0.0.1.dist-info/LICENSE
target_universal_file-0.0.1.dist-info/METADATA
target_universal_file-0.0.1.dist-info/WHEEL
target_universal_file-0.0.1.dist-info/entry_points.txt
target_universal_file-0.0.1.dist-info/RECORD
