Metadata-Version: 2.3
Name: target-universal-file
Version: 0.0.1
Summary: Singer target for any file type on any file system.
License: Apache-2.0
Keywords: ELT
Author: Talia Smiley
Author-email: firstname.lastname@example.com
Requires-Python: >=3.9,<4.0
Classifier: Intended Audience :: Developers
Classifier: License :: OSI Approved :: Apache Software License
Classifier: Operating System :: OS Independent
Classifier: Programming Language :: Python :: 3
Classifier: Programming Language :: Python :: 3.9
Classifier: Programming Language :: Python :: 3.10
Classifier: Programming Language :: Python :: 3.11
Classifier: Programming Language :: Python :: 3.12
Classifier: Programming Language :: Python :: 3.13
Provides-Extra: gcs
Provides-Extra: s3
Requires-Dist: aiobotocore (>=2.21.1) ; extra == "s3"
Requires-Dist: fsspec (>=2025.3.2)
Requires-Dist: gcsfs (>=2025.3.2) ; extra == "gcs"
Requires-Dist: pyarrow (>=19.0.1,<19.1.0)
Requires-Dist: pyarrow-stubs (>=19.1,<20.0)
Requires-Dist: requests (>=2.32.3,<2.33.0)
Requires-Dist: s3fs (>=2025.3.2) ; extra == "s3"
Requires-Dist: singer-sdk[faker] (>=0.45.10,<0.46.0)
Requires-Dist: xlsxwriter (>=3.2.3,<3.3.0)
